litterate/__init__.py
litterate/cli.py
litterate/defaults.py
litterate/generator.py
litterate/templates/index.html
litterate/templates/main.css
litterate/templates/source.html
litterate-0.1.0.dist-info/METADATA
litterate-0.1.0.dist-info/WHEEL
litterate-0.1.0.dist-info/entry_points.txt
litterate-0.1.0.dist-info/licenses/LICENSE
litterate-0.1.0.dist-info/RECORD
