Metadata-Version: 2.4
Name: litterate
Version: 0.1.0
Summary: Generate beautiful literate programming-style description of your code from comment annotations
Project-URL: Homepage, https://github.com/thesephist/litterate
Project-URL: Repository, https://github.com/thesephist/litterate
Author: James
License: MIT
License-File: LICENSE
Keywords: code-annotation,documentation,literate-programming
Classifier: Development Status :: 4 - Beta
Classifier: Intended Audience :: Developers
Classifier: License :: OSI Approved :: MIT License
Classifier: Programming Language :: Python :: 3
Classifier: Programming Language :: Python :: 3.11
Classifier: Programming Language :: Python :: 3.12
Classifier: Topic :: Documentation
Classifier: Topic :: Software Development :: Documentation
Requires-Python: >=3.11
Requires-Dist: click>=8.1
Requires-Dist: jinja2>=3.1
Requires-Dist: markdown>=3.5
Provides-Extra: dev
Requires-Dist: pytest>=7.4; extra == 'dev'
Requires-Dist: ruff>=0.1; extra == 'dev'
